unificontrol/__init__.py
unificontrol/constants.py
unificontrol/exceptions.py
unificontrol/json_fixers.py
unificontrol/metaprogram.py
unificontrol/pinned_requests.py
unificontrol/unifi.py
unificontrol-0.2.9.dist-info/LICENSE.txt
unificontrol-0.2.9.dist-info/METADATA
unificontrol-0.2.9.dist-info/WHEEL
unificontrol-0.2.9.dist-info/top_level.txt
unificontrol-0.2.9.dist-info/RECORD
