Metadata-Version: 2.1
Name: unificontrol
Version: 0.2.9
Summary: Secure access to Ubiquiti Unifi network controllers
Home-page: https://github.com/nickovs/unificontrol
Author: Nicko van Someren
Author-email: nicko@nicko.org
License: UNKNOWN
Keywords: unifi,wifi,network,mamangement
Platform: UNKNOWN
Classifier: Development Status :: 4 - Beta
Classifier: Programming Language :: Python :: 3
Classifier: License :: OSI Approved :: Apache Software License
Classifier: Operating System :: OS Independent
Requires-Python: >=3.4
Requires-Dist: requests
